troveextractor/__init__.py
troveextractor/main.py
troveextractor-0.1.0.dist-info/METADATA
troveextractor-0.1.0.dist-info/WHEEL
troveextractor-0.1.0.dist-info/top_level.txt
troveextractor-0.1.0.dist-info/RECORD
